LetterRip.py
LetterRip-0.0.1.dist-info/METADATA
LetterRip-0.0.1.dist-info/WHEEL
LetterRip-0.0.1.dist-info/top_level.txt
LetterRip-0.0.1.dist-info/RECORD
