Metadata-Version: 2.1
Name: LetterRip
Version: 0.0.1
Summary: Let Numpy Decide!
Home-page: UNKNOWN
Author: UNKNOWN
Author-email: UNKNOWN
License: UNKNOWN
Platform: UNKNOWN
